indico_custom_footer/__about__.py
indico_custom_footer/__init__.py
indico_custom_footer/forms.py
indico_custom_footer/plugin.py
indico_custom_footer/utility.py
indico_plugin_custom_footer-2.0.1.dist-info/DESCRIPTION.rst
indico_plugin_custom_footer-2.0.1.dist-info/METADATA
indico_plugin_custom_footer-2.0.1.dist-info/RECORD
indico_plugin_custom_footer-2.0.1.dist-info/WHEEL
indico_plugin_custom_footer-2.0.1.dist-info/entry_points.txt
indico_plugin_custom_footer-2.0.1.dist-info/metadata.json
indico_plugin_custom_footer-2.0.1.dist-info/top_level.txt
indico_plugin_custom_footer-2.0.1.dist-info/zip-safe
