Metadata-Version: 2.0
Name: indico-plugin-custom-footer
Version: 2.0.1
Summary: Indico Footer Customisation Plugin
Home-page: https://github.com/MaineKuehn/indico_footer
Author: Eileen Kuehn, Max Fischer
Author-email: eileen.kuehn@kit.edu
License: GPLv3+
Keywords: indico customisation footer html plugin
Platform: UNKNOWN
Classifier: Development Status :: 5 - Production/Stable
Classifier: Environment :: Plugins
Classifier: Environment :: Web Environment
Classifier: Intended Audience :: Science/Research
Classifier: Intended Audience :: System Administrators
Classifier: Intended Audience :: Other Audience
Classifier: License :: OSI Approved :: GNU General Public License v3 or later (GPLv3+)
Classifier: Operating System :: OS Independent
Classifier: Programming Language :: Python :: 2.7
Classifier: Topic :: Communications :: Conferencing
Classifier: Topic :: Internet :: WWW/HTTP :: WSGI :: Application
Requires-Dist: indico (>=2.0)
